pymbar/__init__.py
pymbar/_version.py
pymbar/confidenceintervals.py
pymbar/fes.py
pymbar/mbar.py
pymbar/mbar_solvers.py
pymbar/other_estimators.py
pymbar/timeseries.py
pymbar/utils.py
pymbar/utils_for_testing.py
pymbar/version.py
pymbar/tests/__init__.py
pymbar/tests/test_bar.py
pymbar/tests/test_covariance.py
pymbar/tests/test_exp.py
pymbar/tests/test_fes.py
pymbar/tests/test_mbar.py
pymbar/tests/test_mbar_solvers.py
pymbar/tests/test_timeseries.py
pymbar/tests/test_utils.py
pymbar/testsystems/__init__.py
pymbar/testsystems/exponential_distributions.py
pymbar/testsystems/gaussian_work.py
pymbar/testsystems/harmonic_oscillators.py
pymbar/testsystems/timeseries.py
pymbar-4.0.3.dist-info/LICENSE
pymbar-4.0.3.dist-info/METADATA
pymbar-4.0.3.dist-info/WHEEL
pymbar-4.0.3.dist-info/top_level.txt
pymbar-4.0.3.dist-info/RECORD
